{"Header": ["22e RALLYE MONTE CARLO HISTORIQUE 2019", "", "", "", "", "", "Secteur : \u00ab CALAIS - REIMS \u00bb :\n", "", "269,00 km - Temps Id\u00e9al : 7 h 50"], "Footer": ["Cartes Michelin n\u00b0 301 - 302 - 306\n", "", "", ""], "HeaderMods": ["0 1 0", "0 0 0", "0 0 0", "0 0 0", "0 0 0", "0 0 0", "0 1 0", "0 0 0", "0 1 0"], "FooterMods": ["1 0 0", "0 0 0", "0 0 0", "0 0 0"], "Table": [["\ufeffFrance", "", "", "", "", ""], ["Pas-de-Calais", "CALAIS", "", "", "940", "de 12 h 30 \u00e0 12 h 39"], ["\\hline", "", "", "", "", ""], ["CH", "CALAIS", "E 15 / A 26", "0", "0", "de 12 h 30 \u00e0 12 h 39"], ["Pas-de-Calais", "(B\u00e9thune)", "E 15 / A 26", "70", "70", ""], ["\\hline", "", "", "", "", ""], ["Nord", "(Cambrai)", "E 15 / A 26", "69", "139", ""], ["\\hline", "", "", "", "", ""], ["Aisne", "(St-Quentin)", "E 17 /A26", "31", "170", ""], ["", "(Laon)", "E 17 /A26", "54", "224", ""], ["\\hline", "", "", "", "", ""], ["", "La neuvillette", "D944 / D44", "39", "263", ""], ["Marne     CH", "REIMS", "", "6", "269", "de 12 h 30 \u00e0 12 h 39"]], "ItineraryName": "GLASGOW - 2"}